MCSContent.py
__init__.py
content.py
MCSContent-1.0.dist-info/LICENSE
MCSContent-1.0.dist-info/METADATA
MCSContent-1.0.dist-info/WHEEL
MCSContent-1.0.dist-info/top_level.txt
MCSContent-1.0.dist-info/RECORD
