Metadata-Version: 2.1
Name: MCSContent
Version: 1.0
Summary: This is a module used to simplify what is returned by the MCStutas module
Home-page: https://fengrui.link
Author: Ray
Author-email: fengrui@fengrui.asia
License: LICENSE
License-File: LICENSE
